sphinxcontrib_emacs-0.4-py2.7-nspkg.pth
sphinxcontrib/emacs/__init__.py
sphinxcontrib/emacs/domain.py
sphinxcontrib/emacs/info.py
sphinxcontrib/emacs/nodes.py
sphinxcontrib/emacs/roles.py
sphinxcontrib/emacs/util.py
sphinxcontrib/emacs/directives/__init__.py
sphinxcontrib/emacs/directives/desc.py
sphinxcontrib/emacs/directives/other.py
sphinxcontrib/emacs/lisp/__init__.py
sphinxcontrib/emacs/lisp/docstring.py
sphinxcontrib/emacs/lisp/util.py
sphinxcontrib/emacs/visitors/__init__.py
sphinxcontrib/emacs/visitors/html.py
sphinxcontrib/emacs/visitors/latex.py
sphinxcontrib/emacs/visitors/texinfo.py
sphinxcontrib_emacs-0.4.dist-info/DESCRIPTION.rst
sphinxcontrib_emacs-0.4.dist-info/METADATA
sphinxcontrib_emacs-0.4.dist-info/RECORD
sphinxcontrib_emacs-0.4.dist-info/WHEEL
sphinxcontrib_emacs-0.4.dist-info/metadata.json
sphinxcontrib_emacs-0.4.dist-info/namespace_packages.txt
sphinxcontrib_emacs-0.4.dist-info/top_level.txt
