Metadata-Version: 2.0
Name: sphinxcontrib-emacs
Version: 0.4
Summary: Emacs documentation support for Sphinx
Home-page: https://github.com/sambrightman/sphinxcontrib-emacs
Author: Sebastian Wiesner
Author-email: swiesner@lunaryorn.com
License: MIT License
Platform: any
Classifier: Development Status :: 3 - Alpha
Classifier: Intended Audience :: Developers
Classifier: License :: OSI Approved :: MIT License
Classifier: Operating System :: OS Independent
Classifier: Programming Language :: Emacs-Lisp
Classifier: Programming Language :: Python
Classifier: Programming Language :: Python :: 2
Classifier: Programming Language :: Python :: 2 :: Only
Classifier: Topic :: Documentation
Classifier: Topic :: Text Editors :: Emacs
Requires-Dist: Sphinx (>=1.2)
Requires-Dist: sexpdata (>=0.0.3)
Requires-Dist: requests (>=2.2)
